qmasm/__init__.py
qmasm/__main__.py
qmasm/assertions.py
qmasm/cmdline.py
qmasm/output.py
qmasm/parse.py
qmasm/problem.py
qmasm/solutions.py
qmasm/solve.py
qmasm/utils.py
qmasm-4.1.data/scripts/qb2qmasm
qmasm-4.1.data/scripts/qmasm-gen-all-to-all
qmasm-4.1.data/scripts/qmasm-gen-chimera
qmasm-4.1.data/scripts/qmasm-gen-current
qmasm-4.1.dist-info/LICENSE.md
qmasm-4.1.dist-info/METADATA
qmasm-4.1.dist-info/WHEEL
qmasm-4.1.dist-info/entry_points.txt
qmasm-4.1.dist-info/top_level.txt
qmasm-4.1.dist-info/RECORD
