Metadata-Version: 2.1
Name: qmasm
Version: 4.1
Summary: Quantum Macro Assembler
Home-page: https://github.com/lanl/qmasm
Author: Scott Pakin
Author-email: pakin@lanl.gov
License: BSD-ish
Download-URL: https://github.com/lanl/qmasm/archive/v4.1.tar.gz
Keywords: quantum,annealing,macro,assembler,d-wave
Platform: UNKNOWN
Classifier: Topic :: Software Development :: Compilers
Classifier: Development Status :: 5 - Production/Stable
Classifier: Environment :: Console
Classifier: Programming Language :: Python :: 3
Classifier: Intended Audience :: Developers
Requires-Python: >= 3.8
Requires-Dist: dwave-ocean-sdk
